levo_commons/__init__.py
levo_commons/config.py
levo_commons/cwe.py
levo_commons/events.py
levo_commons/failures.py
levo_commons/models.py
levo_commons/params.py
levo_commons/providers.py
levo_commons/request_utils.py
levo_commons/status.py
levo_commons/types.py
levo_commons/utils.py
levo_commons-0.2.28.dist-info/METADATA
levo_commons-0.2.28.dist-info/WHEEL
levo_commons-0.2.28.dist-info/top_level.txt
levo_commons-0.2.28.dist-info/RECORD
