Metadata-Version: 2.4
Name: levo_commons
Version: 0.2.28
Summary: Common code between Levo CLI and test plans.
Home-page: https://github.com/levoai/levo-commons
Author: Levo Inc
Author-email: info@levo.ai
Project-URL: Bug Tracker, https://github.com/levo/levo-commons/issues
Classifier: Programming Language :: Python :: 3
Classifier: License :: OSI Approved :: MIT License
Classifier: Operating System :: OS Independent
Requires-Python: >=3.9
Requires-Dist: attrs>=20.3
Requires-Dist: curlify>=2.2.1
Requires-Dist: grpcio<2.0.0,>=1.37.0
Requires-Dist: requests>=2.25.1
Provides-Extra: test
Requires-Dist: pytest>=6.0; extra == "test"
Requires-Dist: hypothesis<7.0.0,>=6.14.3; extra == "test"
Dynamic: author
Dynamic: author-email
Dynamic: classifier
Dynamic: description
Dynamic: description-content-type
Dynamic: home-page
Dynamic: project-url
Dynamic: provides-extra
Dynamic: requires-dist
Dynamic: requires-python
Dynamic: summary
